[
 {
  "block_modules": [
   {
    "module": "Accounts",
    "parent": "E360 Module",
    "parentfield": "block_modules",
    "parenttype": "Module Profile"
   },
   {
    "module": "Assets",
    "parent": "E360 Module",
    "parentfield": "block_modules",
    "parenttype": "Module Profile"
   },
   {
    "module": "Automation",
    "parent": "E360 Module",
    "parentfield": "block_modules",
    "parenttype": "Module Profile"
   },
   {
    "module": "Bulk Transaction",
    "parent": "E360 Module",
    "parentfield": "block_modules",
    "parenttype": "Module Profile"
   },
   {
    "module": "Buying",
    "parent": "E360 Module",
    "parentfield": "block_modules",
    "parenttype": "Module Profile"
   },
   {
    "module": "Communication",
    "parent": "E360 Module",
    "parentfield": "block_modules",
    "parenttype": "Module Profile"
   },
   {
    "module": "Contacts",
    "parent": "E360 Module",
    "parentfield": "block_modules",
    "parenttype": "Module Profile"
   },
   {
    "module": "Core",
    "parent": "E360 Module",
    "parentfield": "block_modules",
    "parenttype": "Module Profile"
   },
   {
    "module": "CRM",
    "parent": "E360 Module",
    "parentfield": "block_modules",
    "parenttype": "Module Profile"
   },
   {
    "module": "Custom",
    "parent": "E360 Module",
    "parentfield": "block_modules",
    "parenttype": "Module Profile"
   },
   {
    "module": "Email",
    "parent": "E360 Module",
    "parentfield": "block_modules",
    "parenttype": "Module Profile"
   },
   {
    "module": "ERPNext Integrations",
    "parent": "E360 Module",
    "parentfield": "block_modules",
    "parenttype": "Module Profile"
   },
   {
    "module": "Geo",
    "parent": "E360 Module",
    "parentfield": "block_modules",
    "parenttype": "Module Profile"
   },
   {
    "module": "Integrations",
    "parent": "E360 Module",
    "parentfield": "block_modules",
    "parenttype": "Module Profile"
   },
   {
    "module": "Maintenance",
    "parent": "E360 Module",
    "parentfield": "block_modules",
    "parenttype": "Module Profile"
   },
   {
    "module": "Manufacturing",
    "parent": "E360 Module",
    "parentfield": "block_modules",
    "parenttype": "Module Profile"
   },
   {
    "module": "Portal",
    "parent": "E360 Module",
    "parentfield": "block_modules",
    "parenttype": "Module Profile"
   },
   {
    "module": "Printing",
    "parent": "E360 Module",
    "parentfield": "block_modules",
    "parenttype": "Module Profile"
   },
   {
    "module": "Projects",
    "parent": "E360 Module",
    "parentfield": "block_modules",
    "parenttype": "Module Profile"
   },
   {
    "module": "Quality Management",
    "parent": "E360 Module",
    "parentfield": "block_modules",
    "parenttype": "Module Profile"
   },
   {
    "module": "Regional",
    "parent": "E360 Module",
    "parentfield": "block_modules",
    "parenttype": "Module Profile"
   },
   {
    "module": "Selling",
    "parent": "E360 Module",
    "parentfield": "block_modules",
    "parenttype": "Module Profile"
   },
   {
    "module": "Setup",
    "parent": "E360 Module",
    "parentfield": "block_modules",
    "parenttype": "Module Profile"
   },
   {
    "module": "Social",
    "parent": "E360 Module",
    "parentfield": "block_modules",
    "parenttype": "Module Profile"
   },
   {
    "module": "Stock",
    "parent": "E360 Module",
    "parentfield": "block_modules",
    "parenttype": "Module Profile"
   },
   {
    "module": "Subcontracting",
    "parent": "E360 Module",
    "parentfield": "block_modules",
    "parenttype": "Module Profile"
   },
   {
    "module": "Support",
    "parent": "E360 Module",
    "parentfield": "block_modules",
    "parenttype": "Module Profile"
   },
   {
    "module": "Telephony",
    "parent": "E360 Module",
    "parentfield": "block_modules",
    "parenttype": "Module Profile"
   },
   {
    "module": "Utilities",
    "parent": "E360 Module",
    "parentfield": "block_modules",
    "parenttype": "Module Profile"
   },
   {
    "module": "Website",
    "parent": "E360 Module",
    "parentfield": "block_modules",
    "parenttype": "Module Profile"
   },
   {
    "module": "Workflow",
    "parent": "E360 Module",
    "parentfield": "block_modules",
    "parenttype": "Module Profile"
   },
   {
    "module": "Desk",
    "parent": "E360 Module",
    "parentfield": "block_modules",
    "parenttype": "Module Profile"
   },
   {
    "module": "E360",
    "parent": "E360 Module",
    "parentfield": "block_modules",
    "parenttype": "Module Profile"
   }
  ],
  "docstatus": 0,
  "doctype": "Module Profile",
  "modified": "2025-04-09 10:11:42.136890",
  "module_profile_name": "E360 Module",
  "name": "E360 Module"
 }
]